hydro_topo/__init__.py
hydro_topo/cli.py
hydro_topo/ig_path.py
hydro_topo/ig_path_test.py
hydro_topo-0.0.2.dist-info/LICENSE
hydro_topo-0.0.2.dist-info/METADATA
hydro_topo-0.0.2.dist-info/WHEEL
hydro_topo-0.0.2.dist-info/entry_points.txt
hydro_topo-0.0.2.dist-info/top_level.txt
hydro_topo-0.0.2.dist-info/RECORD
